{
  "name": "Fanny Zimmerman",
  "age": 64,
  "address": {
    "street": "Kicku Path",
    "city": "Amlasan",
    "state": "MO",
    "zip": "96923"
  },
  "contact": {
    "phone": "(889) 607-8181",
    "servicePhone": "800327945"
  },
  "birthday": "1976-03-31T13:49:13.924Z",
  "ip": "61.134.204.31",
  "foo": "bar",
  "profile": {
    "about": "Ec heonaoso betpu utidivena ubmicbi du em ofagenki toro vozan na raw wom. Azuto muwkiudo nicjav fovir amucatif de jovu civaw ba botol lotuhgef oruka rabarle inuje. Lufgizis ji veku va etifel zo banjakpez buw duk ew rov tini sohedif genikuwa weg vafeh. Jek zitomesu ucvuom se goodlu suj heol becimep zum il esme ileita bacjuow jelwiz pubi.",
    "bio": "Mamajek roat ce goh uzimosor pemner jisozva esvaji gumagu tomnizku omcotzom domi. Vemke kufno im ce ehilegki lo ojajolet raepewi puc lic ra boludo ov. Rekdab onfeh wekejtu tal vez amtisiv cofub sepodemeg ji gofa wagi odaisine ifebuku parlev."
  },
  "apiKey": "03e6b01673ab437c22007770be33319e70e8d41e5cfdbb68702647be635dab9d",
  "currency": {
    "code": "MXN",
    "name": "Mexico Peso"
  }
}